ohmytmp_plugins/gui/__init__.py
ohmytmp_plugins/gui/gui.py
ohmytmp_plugins/gui/img.html
ohmytmp_gui-0.0.2.dist-info/LICENSE
ohmytmp_gui-0.0.2.dist-info/METADATA
ohmytmp_gui-0.0.2.dist-info/WHEEL
ohmytmp_gui-0.0.2.dist-info/top_level.txt
ohmytmp_gui-0.0.2.dist-info/RECORD
