Metadata-Version: 2.1
Name: ohmytmp-gui
Version: 0.0.2
Summary: ohmytmp plugin gui
Author-email: userElaina <userelaina@pm.me>
Maintainer-email: userElaina <userelaina@pm.me>
License: MIT License
Project-URL: Homepage, https://github.com/ohmytmp/plugin-gui
Project-URL: Bug Reports, https://github.com/ohmytmp/plugin-gui/issues
Project-URL: Source, https://github.com/ohmytmp/plugin-gui
Keywords: ohmytmp
Classifier: License :: OSI Approved :: MIT License
Classifier: Programming Language :: Python :: 3
Requires-Python: >=3.7
License-File: LICENSE
Requires-Dist: flask
Requires-Dist: ohmytmp (>=0.0.5)
Requires-Dist: ohmytmp-simimg (>=0.0.2)
Requires-Dist: ohmytmp-taggy (>=0.0.2)
